gbmessclient12345/__init__.py
gbmessclient12345/client.py
gbmessclient12345/client/__init__.py
gbmessclient12345/client/app.py
gbmessclient12345/client/config.py
gbmessclient12345/client/controller.py
gbmessclient12345/client/errors.py
gbmessclient12345/client/logger.py
gbmessclient12345/client/transport.py
gbmessclient12345/client/auth/__init__.py
gbmessclient12345/client/auth/app.py
gbmessclient12345/client/auth/gui.py
gbmessclient12345/client/db/__init__.py
gbmessclient12345/client/db/model.py
gbmessclient12345/client/db/view.py
gbmessclient12345/client/gui/__init__.py
gbmessclient12345/client/gui/app.py
gbmessclient12345/client/gui/controller.py
gbmessclient12345/client/gui/model.py
gbmessclient12345/client/gui/view.py
gbmessclient12345/common/__init__.py
gbmessclient12345/common/transport/__init__.py
gbmessclient12345/common/transport/descriptors.py
gbmessclient12345/common/transport/endpoints.py
gbmessclient12345/common/transport/errors.py
gbmessclient12345/common/transport/metaclasses.py
gbmessclient12345/common/transport/protocol.py
gbmessclient12345/common/transport/security.py
gbmessclient12345/common/transport/model/__init__.py
gbmessclient12345/common/transport/model/message.py
gbmessclient12345/common/transport/model/user.py
gbmessclient12345/common/transport/serializers/__init__.py
gbmessclient12345/common/transport/serializers/message.py
gbmessclient12345/common/transport/serializers/user.py
gbmessclient12345/common/utils/__init__.py
gbmessclient12345/common/utils/debug_decorators.py
gbmessclient12345/common/utils/observer.py
gbmessclient12345/common/utils/security.py
gbmessclient12345-0.1.2.dist-info/METADATA
gbmessclient12345-0.1.2.dist-info/WHEEL
gbmessclient12345-0.1.2.dist-info/top_level.txt
gbmessclient12345-0.1.2.dist-info/RECORD
